.installed.cfg
.mr.developer.cfg
LICENSE.txt
MANIFEST.in
README.rst
bootstrap.py
buildout-before-patch.cfg
buildout.cfg
develop.cfg
setup.py
version.txt
doc/conf.py
doc/index.rst
doc/installation.rst
doc/links.rst
doc/py_api.rst
patch/__init__.py
patch/facereclib.patch
xfacereclib/__init__.py
xfacereclib.extension.CSU.egg-info/PKG-INFO
xfacereclib.extension.CSU.egg-info/SOURCES.txt
xfacereclib.extension.CSU.egg-info/dependency_links.txt
xfacereclib.extension.CSU.egg-info/entry_points.txt
xfacereclib.extension.CSU.egg-info/namespace_packages.txt
xfacereclib.extension.CSU.egg-info/requires.txt
xfacereclib.extension.CSU.egg-info/top_level.txt
xfacereclib/extension/__init__.py
xfacereclib/extension/CSU/__init__.py
xfacereclib/extension/CSU/configurations.py
xfacereclib/extension/CSU/ldair.py
xfacereclib/extension/CSU/lrpca.py
xfacereclib/extension/CSU/tests.py
xfacereclib/extension/CSU/testdata/testimage.png
xfacereclib/extension/CSU/testdata/testimage.pos
xfacereclib/extension/CSU/testdata/features/ldair.pkl
xfacereclib/extension/CSU/testdata/features/ldair_extractor.pkl
xfacereclib/extension/CSU/testdata/features/lrpca.hdf5
xfacereclib/extension/CSU/testdata/features/lrpca_extractor.pkl
xfacereclib/extension/CSU/testdata/preprocessing/ldair.hdf5
xfacereclib/extension/CSU/testdata/preprocessing/lrpca.hdf5
xfacereclib/extension/CSU/testdata/tool/ldair_model.pkl
xfacereclib/extension/CSU/testdata/tool/lrpca_model.pkl