Metadata-Version: 1.1
Name: xfacereclib.extension.CSU
Version: 2.0.0
Summary: Wrapper classes to use the PythonFaceEvaluation classes from the CSU Face Recognition Resources
Home-page: http://github.com/bioidiap/xfacereclib.extension.CSU
Author: Manuel Guenther
Author-email: manuel.guenther@idiap.ch
License: GPLv3
Platform: UNKNOWN
Classifier: Framework :: Bob
Classifier: Development Status :: 4 - Beta
Classifier: Intended Audience :: Science/Research
Classifier: License :: OSI Approved :: GNU General Public License v3 (GPLv3)
Classifier: Natural Language :: English
Classifier: Programming Language :: Python :: 2.7
Classifier: Environment :: Console
Classifier: Framework :: Buildout
Classifier: Topic :: Scientific/Engineering
